beamr/__init__.py
beamr/__main__.py
beamr/cli.py
beamr/debug.py
beamr/interpreters/__init__.py
beamr/interpreters/config.py
beamr/interpreters/hierarchical.py
beamr/interpreters/textual.py
beamr/lexers/__init__.py
beamr/lexers/document.py
beamr/lexers/generic.py
beamr/lexers/image.py
beamr/lexers/slide.py
beamr/parsers/__init__.py
beamr/parsers/document.py
beamr/parsers/document_parsetab.py
beamr/parsers/generic.py
beamr/parsers/image.py
beamr/parsers/image_parsetab.py
beamr/parsers/slide.py
beamr/parsers/slide_parsetab.py
Beamr-0.4.0.dist-info/LICENSE
Beamr-0.4.0.dist-info/METADATA
Beamr-0.4.0.dist-info/WHEEL
Beamr-0.4.0.dist-info/entry_points.txt
Beamr-0.4.0.dist-info/top_level.txt
Beamr-0.4.0.dist-info/RECORD
